_psmqtt_version.py
psmqtt/__init__.py
psmqtt/config.py
psmqtt/formatter.py
psmqtt/formatter_test.py
psmqtt/ha_units.py
psmqtt/handlers_base.py
psmqtt/handlers_base_test.py
psmqtt/handlers_derived.py
psmqtt/handlers_derived_test.py
psmqtt/handlers_embedded.py
psmqtt/handlers_embedded_test.py
psmqtt/handlers_psutil.py
psmqtt/handlers_psutil_processes.py
psmqtt/handlers_psutil_processes_test.py
psmqtt/handlers_psutil_test.py
psmqtt/handlers_pysmart.py
psmqtt/handlers_pysmart_test.py
psmqtt/main.py
psmqtt/mqtt_client.py
psmqtt/psmqtt_app.py
psmqtt/schedule.py
psmqtt/schedule_test.py
psmqtt/task.py
psmqtt/task_test.py
psmqtt/topic.py
psmqtt/topic_test.py
psmqtt/utils.py
psmqtt/schema/psmqtt.schema.yaml
psmqtt-2.6.1.dist-info/METADATA
psmqtt-2.6.1.dist-info/WHEEL
psmqtt-2.6.1.dist-info/entry_points.txt
psmqtt-2.6.1.dist-info/licenses/LICENSE
psmqtt-2.6.1.dist-info/RECORD
