Metadata-Version: 2.4
Name: psmqtt
Version: 2.6.1
Summary: Utility reporting system health and status via MQTT
Project-URL: Homepage, https://github.com/eschava/psmqtt
Project-URL: Bug Tracker, https://github.com/eschava/psmqtt/issues
Author-email: Eugene Schava <eschava.nospam@gmail.com>, Francesco Montorsi <francesco.montorsi.nospam@gmail.com>
License-File: LICENSE
Classifier: License :: OSI Approved :: MIT License
Classifier: Operating System :: OS Independent
Classifier: Programming Language :: Python :: 3
Requires-Python: >=3.10
Requires-Dist: jinja2==3.1.6
Requires-Dist: paho-mqtt==2.1.0
Requires-Dist: platformdirs==4.5.1
Requires-Dist: psutil==7.0.0
Requires-Dist: pysmart==1.4.2
Requires-Dist: python-dateutil==2.9.0.post0
Requires-Dist: pyyaml==6.0.3
Requires-Dist: recurrent==0.4.1
Requires-Dist: testcontainers==4.14.0
Requires-Dist: types-paho-mqtt==1.6.0.20240321
Requires-Dist: yamale==6.1.0
